clighter/__init__.py
clighter/cli/__init__.py
clighter/cli/game.py
clighter/cli/input.py
clighter/cli/scene.py
clighter/cli/util/__init__.py
clighter/cli/util/stdin.py
clighter/cli/util/stdout.py
clighter/core/__init__.py
clighter/core/animation.py
clighter/core/common.py
clighter/core/dimension.py
clighter/core/engine.py
clighter/core/factory.py
clighter/core/game.py
clighter/core/input.py
clighter/core/object.py
clighter/core/position.py
clighter/core/rect.py
clighter/core/scene.py
clighter/core/util/__init__.py
clighter/core/util/collections.py
clighter/core/util/files.py
clighter/core/util/singleton.py
clighter-0.3.5.dist-info/LICENSE
clighter-0.3.5.dist-info/METADATA
clighter-0.3.5.dist-info/WHEEL
clighter-0.3.5.dist-info/top_level.txt
clighter-0.3.5.dist-info/RECORD
