Metadata-Version: 2.1
Name: clighter
Version: 0.3.5
Summary: 'Game engine for CLI games.'
Home-page: https://github.com/bilginyuksel/clighter
Author: bilginyuksel
Author-email: bilgin.yuksel96@gmail.com
License: UNKNOWN
Project-URL: Bug Tracker, https://github.com/bilginyuksel/clighter/issues
Platform: UNKNOWN
Classifier: Programming Language :: Python :: 3
Classifier: License :: OSI Approved :: Apache Software License
Classifier: Operating System :: OS Independent
Requires-Python: >=3.6
License-File: LICENSE
